[
  {
    "edges": 1,
    "nodes": 2,
    "exits": 1,
    "c": 0,
    "shortName": "[[constants.js]]",
    "name": "[[constants.js]]",
    "s": 59,
    "b": 0,
    "anons": 1,
    "depth": 0,
    "blockDepth": 0,
    "lineStart": 1,
    "comments": 0,
    "lineEnd": 105,
    "operatorCount": 6,
    "operandCount": 4,
    "operators": {
      "=": true,
      "{": true,
      "(": true
    },
    "operands": {
      "module": true,
      "exports": true,
      "call": true,
      "this": true
    },
    "ins": 0,
    "complexity": 1,
    "mi": "83.256",
    "halsteadLevel": "0.137",
    "lines": 105,
    "commentPct": 0,
    "halsteadVolume": "34.6",
    "halsteadPotential": "4.75"
  },
  {
    "edges": 1,
    "nodes": 2,
    "exits": 1,
    "c": 0,
    "shortName": "require",
    "name": "[[constants.js]].require",
    "s": 0,
    "b": 0,
    "parent": "[[constants.js]]",
    "anons": 0,
    "depth": 1,
    "blockDepth": 0,
    "lineStart": 1,
    "comments": 0,
    "lineEnd": 1,
    "operatorCount": 0,
    "operandCount": 0,
    "operators": {},
    "operands": {},
    "ins": 0,
    "complexity": 1,
    "mi": "NaN.00",
    "halsteadLevel": 0,
    "lines": 1,
    "commentPct": 0,
    "halsteadVolume": 0,
    "halsteadPotential": 0
  },
  {
    "edges": 1,
    "nodes": 2,
    "exits": 1,
    "c": 0,
    "shortName": "(Anonymous1)",
    "name": "[[constants.js]].(Anonymous1)",
    "s": 56,
    "b": 0,
    "parent": "[[constants.js]]",
    "anons": 4,
    "depth": 1,
    "blockDepth": 0,
    "lineStart": 2,
    "comments": 0,
    "lineEnd": 103,
    "operatorCount": 16,
    "operandCount": 16,
    "operators": {
      "=": true,
      "(": true,
      ".": true
    },
    "operands": {
      "MT": true,
      "exports": true,
      "TAG": true,
      "NUM_BYTES": true,
      "SIMPLE": true
    },
    "ins": 0,
    "complexity": 1,
    "mi": "79.618",
    "halsteadLevel": "0.0413",
    "lines": 102,
    "commentPct": 0,
    "halsteadVolume": "115",
    "halsteadPotential": "4.75"
  },
  {
    "edges": 1,
    "nodes": 2,
    "exits": 2,
    "c": 0,
    "shortName": "MT.(Anonymous1)",
    "name": "[[constants.js]].(Anonymous1).MT.(Anonymous1)",
    "s": 12,
    "b": 0,
    "parent": "[[constants.js]].(Anonymous1)",
    "anons": 0,
    "depth": 2,
    "blockDepth": 0,
    "lineStart": 5,
    "comments": 0,
    "lineEnd": 24,
    "operatorCount": 17,
    "operandCount": 25,
    "operators": {
      "=": true,
      ".": true,
      "return": true
    },
    "operands": {
      "0": true,
      "1": true,
      "2": true,
      "3": true,
      "4": true,
      "5": true,
      "6": true,
      "7": true,
      "MT": true,
      "POS_INT": true,
      "NEG_INT": true,
      "BYTE_STRING": true,
      "UTF8_STRING": true,
      "ARRAY": true,
      "MAP": true,
      "TAG": true,
      "SIMPLE_FLOAT": true
    },
    "ins": 0,
    "complexity": 2,
    "mi": "104.01",
    "halsteadLevel": "0.0246",
    "lines": 20,
    "commentPct": 0,
    "halsteadVolume": "193",
    "halsteadPotential": "4.75"
  },
  {
    "edges": 1,
    "nodes": 2,
    "exits": 1,
    "c": 0,
    "shortName": "MT.MT",
    "name": "[[constants.js]].(Anonymous1).MT.(Anonymous1).MT.MT",
    "s": 0,
    "b": 0,
    "parent": "[[constants.js]].(Anonymous1).MT.(Anonymous1)",
    "anons": 0,
    "depth": 3,
    "blockDepth": 0,
    "lineStart": 6,
    "comments": 0,
    "lineEnd": 6,
    "operatorCount": 0,
    "operandCount": 0,
    "operators": {},
    "operands": {},
    "ins": 0,
    "complexity": 1,
    "mi": "NaN.00",
    "halsteadLevel": 0,
    "lines": 1,
    "commentPct": 0,
    "halsteadVolume": 0,
    "halsteadPotential": 0
  },
  {
    "edges": 1,
    "nodes": 2,
    "exits": 2,
    "c": 0,
    "shortName": "TAG.(Anonymous2)",
    "name": "[[constants.js]].(Anonymous1).TAG.(Anonymous2)",
    "s": 19,
    "b": 0,
    "parent": "[[constants.js]].(Anonymous1)",
    "anons": 0,
    "depth": 2,
    "blockDepth": 0,
    "lineStart": 30,
    "comments": 0,
    "lineEnd": 63,
    "operatorCount": 31,
    "operandCount": 46,
    "operators": {
      "=": true,
      ".": true,
      "return": true
    },
    "operands": {
      "0": true,
      "1": true,
      "2": true,
      "3": true,
      "4": true,
      "5": true,
      "21": true,
      "22": true,
      "23": true,
      "24": true,
      "32": true,
      "33": true,
      "34": true,
      "35": true,
      "36": true,
      "TAG": true,
      "DATE_STRING": true,
      "DATE_EPOCH": true,
      "POS_BIGINT": true,
      "NEG_BIGINT": true,
      "DECIMAL_FRAC": true,
      "BIGFLOAT": true,
      "BASE64URL_EXPECTED": true,
      "BASE64_EXPECTED": true,
      "BASE16_EXPECTED": true,
      "CBOR": true,
      "URI": true,
      "BASE64URL": true,
      "BASE64": true,
      "REGEXP": true,
      "MIME": true
    },
    "ins": 0,
    "complexity": 2,
    "mi": "92.888",
    "halsteadLevel": "0.0118",
    "lines": 34,
    "commentPct": 0,
    "halsteadVolume": "404",
    "halsteadPotential": "4.75"
  },
  {
    "edges": 1,
    "nodes": 2,
    "exits": 1,
    "c": 0,
    "shortName": "TAG.TAG",
    "name": "[[constants.js]].(Anonymous1).TAG.(Anonymous2).TAG.TAG",
    "s": 0,
    "b": 0,
    "parent": "[[constants.js]].(Anonymous1).TAG.(Anonymous2)",
    "anons": 0,
    "depth": 3,
    "blockDepth": 0,
    "lineStart": 31,
    "comments": 0,
    "lineEnd": 31,
    "operatorCount": 0,
    "operandCount": 0,
    "operators": {},
    "operands": {},
    "ins": 0,
    "complexity": 1,
    "mi": "NaN.00",
    "halsteadLevel": 0,
    "lines": 1,
    "commentPct": 0,
    "halsteadVolume": 0,
    "halsteadPotential": 0
  },
  {
    "edges": 1,
    "nodes": 2,
    "exits": 2,
    "c": 0,
    "shortName": "NUM_BYTES.(Anonymous3)",
    "name": "[[constants.js]].(Anonymous1).NUM_BYTES.(Anonymous3)",
    "s": 9,
    "b": 0,
    "parent": "[[constants.js]].(Anonymous1)",
    "anons": 0,
    "depth": 2,
    "blockDepth": 0,
    "lineStart": 69,
    "comments": 0,
    "lineEnd": 82,
    "operatorCount": 11,
    "operandCount": 16,
    "operators": {
      "=": true,
      ".": true,
      "return": true
    },
    "operands": {
      "0": true,
      "24": true,
      "25": true,
      "26": true,
      "27": true,
      "NUM_BYTES": true,
      "ZERO": true,
      "ONE": true,
      "TWO": true,
      "FOUR": true,
      "EIGHT": true
    },
    "ins": 0,
    "complexity": 2,
    "mi": "111.62",
    "halsteadLevel": "0.0420",
    "lines": 14,
    "commentPct": 0,
    "halsteadVolume": "113",
    "halsteadPotential": "4.75"
  },
  {
    "edges": 1,
    "nodes": 2,
    "exits": 1,
    "c": 0,
    "shortName": "NUM_BYTES.NUM_BYTES",
    "name": "[[constants.js]].(Anonymous1).NUM_BYTES.(Anonymous3).NUM_BYTES.NUM_BYTES",
    "s": 0,
    "b": 0,
    "parent": "[[constants.js]].(Anonymous1).NUM_BYTES.(Anonymous3)",
    "anons": 0,
    "depth": 3,
    "blockDepth": 0,
    "lineStart": 70,
    "comments": 0,
    "lineEnd": 70,
    "operatorCount": 0,
    "operandCount": 0,
    "operators": {},
    "operands": {},
    "ins": 0,
    "complexity": 1,
    "mi": "NaN.00",
    "halsteadLevel": 0,
    "lines": 1,
    "commentPct": 0,
    "halsteadVolume": 0,
    "halsteadPotential": 0
  },
  {
    "edges": 1,
    "nodes": 2,
    "exits": 2,
    "c": 0,
    "shortName": "SIMPLE.(Anonymous4)",
    "name": "[[constants.js]].(Anonymous1).SIMPLE.(Anonymous4)",
    "s": 8,
    "b": 0,
    "parent": "[[constants.js]].(Anonymous1)",
    "anons": 0,
    "depth": 2,
    "blockDepth": 0,
    "lineStart": 88,
    "comments": 0,
    "lineEnd": 99,
    "operatorCount": 9,
    "operandCount": 13,
    "operators": {
      "=": true,
      ".": true,
      "return": true
    },
    "operands": {
      "20": true,
      "21": true,
      "22": true,
      "23": true,
      "SIMPLE": true,
      "FALSE": true,
      "TRUE": true,
      "NULL": true,
      "UNDEFINED": true
    },
    "ins": 0,
    "complexity": 2,
    "mi": "114.97",
    "halsteadLevel": "0.0540",
    "lines": 12,
    "commentPct": 0,
    "halsteadVolume": "88.0",
    "halsteadPotential": "4.75"
  },
  {
    "edges": 1,
    "nodes": 2,
    "exits": 1,
    "c": 0,
    "shortName": "SIMPLE.SIMPLE",
    "name": "[[constants.js]].(Anonymous1).SIMPLE.(Anonymous4).SIMPLE.SIMPLE",
    "s": 0,
    "b": 0,
    "parent": "[[constants.js]].(Anonymous1).SIMPLE.(Anonymous4)",
    "anons": 0,
    "depth": 3,
    "blockDepth": 0,
    "lineStart": 89,
    "comments": 0,
    "lineEnd": 89,
    "operatorCount": 0,
    "operandCount": 0,
    "operators": {},
    "operands": {},
    "ins": 0,
    "complexity": 1,
    "mi": "NaN.00",
    "halsteadLevel": 0,
    "lines": 1,
    "commentPct": 0,
    "halsteadVolume": 0,
    "halsteadPotential": 0
  }
]